az_container_helper/__init__.py
az_container_helper/keyvault.py
az_container_helper/utils.py
az_container_helper/resources/.gitkeep
az_container_helper-0.1.3.dist-info/METADATA
az_container_helper-0.1.3.dist-info/WHEEL
az_container_helper-0.1.3.dist-info/licenses/LICENSE
az_container_helper-0.1.3.dist-info/RECORD
