Metadata-Version: 2.4
Name: az-container-helper
Version: 0.1.3
Summary: Helper classes and methods for using Azure services from inside a local Docker container.
Author-email: asmaier <asmaier@web.de>
License-Expression: MIT
License-File: LICENSE
Classifier: Development Status :: 4 - Beta
Classifier: Intended Audience :: Developers
Classifier: License :: OSI Approved :: MIT License
Classifier: Natural Language :: English
Classifier: Programming Language :: Python :: 3.11
Classifier: Programming Language :: Python :: 3.12
Classifier: Topic :: Software Development
Classifier: Topic :: Utilities
Requires-Python: >=3.11
Requires-Dist: azure-identity>=1.25.1
Requires-Dist: azure-keyvault-secrets>=4.10.0
Requires-Dist: python-dotenv>=1.2.1
